[
  {
    "id": "1769858652598",
    "name": "Test User",
    "email": "test@example.com",
    "message": "Hello from E2E test",
    "createdAt": "2026-01-31T11:24:12.598Z"
  },
  {
    "id": "1769858684434",
    "name": "Test User",
    "email": "test@example.com",
    "message": "Hello from E2E test",
    "createdAt": "2026-01-31T11:24:44.434Z"
  },
  {
    "id": "1769858720493",
    "name": "Test User",
    "email": "test@example.com",
    "message": "Hello from E2E test",
    "createdAt": "2026-01-31T11:25:20.493Z"
  },
  {
    "id": "1769858758396",
    "name": "Test User",
    "email": "test@example.com",
    "message": "Hello from E2E test",
    "createdAt": "2026-01-31T11:25:58.396Z"
  },
  {
    "id": "1769859605779",
    "name": "Test User",
    "email": "test@example.com",
    "message": "Hello from E2E test",
    "createdAt": "2026-01-31T11:40:05.779Z"
  },
  {
    "id": "1769860715531",
    "name": "Test User",
    "email": "test@example.com",
    "message": "Hello from E2E test",
    "createdAt": "2026-01-31T11:58:35.531Z"
  },
  {
    "id": "1769862557165",
    "name": "Test User",
    "email": "test@example.com",
    "message": "Hello from E2E test",
    "createdAt": "2026-01-31T12:29:17.166Z"
  },
  {
    "id": "1769862611136",
    "name": "Test User",
    "email": "test@example.com",
    "message": "Hello from E2E test",
    "createdAt": "2026-01-31T12:30:11.136Z"
  },
  {
    "id": "1769868776388",
    "name": "Test User",
    "email": "test@example.com",
    "message": "Hello from E2E test",
    "createdAt": "2026-01-31T14:12:56.388Z"
  },
  {
    "id": "1769869320797",
    "name": "Test User",
    "email": "test@example.com",
    "message": "Hello from E2E test",
    "createdAt": "2026-01-31T14:22:00.797Z"
  },
  {
    "id": "1769904945607",
    "name": "Test User",
    "email": "test@example.com",
    "message": "Hello from E2E test",
    "createdAt": "2026-02-01T00:15:45.607Z"
  }
]